CHANGES.txt
DEPENDENCES.txt
README.txt
setup.py
src/ng/__init__.py
src/ng.site.content.egg-info/PKG-INFO
src/ng.site.content.egg-info/SOURCES.txt
src/ng.site.content.egg-info/dependency_links.txt
src/ng.site.content.egg-info/namespace_packages.txt
src/ng.site.content.egg-info/not-zip-safe
src/ng.site.content.egg-info/requires.txt
src/ng.site.content.egg-info/top_level.txt
src/ng/site/__init__.py
src/ng/site/content/__init__.py
src/ng/site/content/configure.zcml
src/ng/site/content/ng.site.content.txt
src/ng/site/content/adapter/__init__.py
src/ng/site/content/adapter/configure.zcml
src/ng/site/content/adapter/convertable2titlesubscriber.py
src/ng/site/content/adapter/doctitle2titleadapter.py
src/ng/site/content/adapter/doctitle2titlesubscriber.py
src/ng/site/content/adapter/readcontainer2pagersourceadapter.py
src/ng/site/content/adaptiveurlroot/__init__.py
src/ng/site/content/adaptiveurlroot/configure.zcml
src/ng/site/content/annotation/__init__.py
src/ng/site/content/annotation/configure.zcml
src/ng/site/content/contain/__init__.py
src/ng/site/content/contain/configure.zcml
src/ng/site/content/convert/__init__.py
src/ng/site/content/convert/configure.zcml
src/ng/site/content/etc/ng.site.content-configure.zcml
src/ng/site/content/etc/ng.site.content-meta.zcml
src/ng/site/content/grant/__init__.py
src/ng/site/content/grant/configure.zcml
src/ng/site/content/install/README.txt
src/ng/site/content/install/__init__.py
src/ng/site/content/install/configure.zcml
src/ng/site/content/install/install_banner.py
src/ng/site/content/install/install_catalog.py
src/ng/site/content/install/install_content.py
src/ng/site/content/install/install_converter.py
src/ng/site/content/install/install_intids.py
src/ng/site/content/install/install_logo.py
src/ng/site/content/install/install_main.py
src/ng/site/content/install/install_objectqueue.py
src/ng/site/content/install/install_registry.py
src/ng/site/content/install/install_rss.py
src/ng/site/content/install/install_sm.py
src/ng/site/content/install/install_smartimage.py
src/ng/site/content/install/interfaces.py
src/ng/site/content/install/rubricdescription.py
src/ng/site/content/install/widgets.py
src/ng/site/content/install/logo/__init__.py
src/ng/site/content/install/logo/banner_thedream_whiteblue.png
